src/__init__.py
src/cfg.py
src/display.py
src/logger.py
src/models.py
src/params.py
src/read_data.py
src/trainer.py
src/utils.py
src/visualize.py
src/wandb_attach.py
test/__init__.py
test/testing.py
trainme-1.0.dist-info/LICENCE
trainme-1.0.dist-info/METADATA
trainme-1.0.dist-info/WHEEL
trainme-1.0.dist-info/top_level.txt
trainme-1.0.dist-info/RECORD
